integration_api/__init__.py
integration_api/api_client.py
integration_api/auth_api.py
integration_api/configuration.py
integration_api/environment.py
integration_api/rest.py
integration_api/api/__init__.py
integration_api/api/accounting_api.py
integration_api/api/ach_api.py
integration_api/api/aggregation_api.py
integration_api/api/async_api.py
integration_api/api/baas_api.py
integration_api/api/brokerage_api.py
integration_api/api/card_api.py
integration_api/api/iav_api.py
integration_api/api/kms_api.py
integration_api/api/kyc_api.py
integration_api/api/market_data_api.py
integration_api/api/rtp_api.py
integration_api/api/sms_api.py
integration_api/api/smtp_api.py
integration_api/api/utils_api.py
integration_api/api/webhook_api.py
integration_api/api/wire_api.py
integration_api/models/__init__.py
integration_api/models/accounting_customer_response_vo.py
integration_api/models/accounting_customer_revenue_response_vo.py
integration_api/models/accounting_final_response_vo.py
integration_api/models/accounting_invoice_payment_response_vo.py
integration_api/models/accounting_invoice_response_vo.py
integration_api/models/accounting_stats_response_vo.py
integration_api/models/ach_balance_response_vo.py
integration_api/models/ach_bank_link_request_co.py
integration_api/models/ach_bank_link_response_vo.py
integration_api/models/ach_beneficial_owner_request_co.py
integration_api/models/ach_beneficial_owner_response_vo.py
integration_api/models/ach_business_balance_response_vo.py
integration_api/models/ach_business_request_co.py
integration_api/models/ach_business_response_vo.py
integration_api/models/ach_card_link_request_co.py
integration_api/models/ach_card_link_response_vo.py
integration_api/models/ach_card_load_response_vo.py
integration_api/models/ach_card_request_co.py
integration_api/models/ach_card_reserve_request_co.py
integration_api/models/ach_card_reserve_response_vo.py
integration_api/models/ach_card_response_vo.py
integration_api/models/ach_client_request_co.py
hydrogen_integration_api-1.3.1.dist-info/METADATA
hydrogen_integration_api-1.3.1.dist-info/WHEEL
hydrogen_integration_api-1.3.1.dist-info/top_level.txt
hydrogen_integration_api-1.3.1.dist-info/RECORD
